pullup/__init__.py
pullup/_modidx.py
pullup/core.py
pullup-0.0.2.dist-info/licenses/LICENSE
pullup-0.0.2.dist-info/METADATA
pullup-0.0.2.dist-info/WHEEL
pullup-0.0.2.dist-info/entry_points.txt
pullup-0.0.2.dist-info/top_level.txt
pullup-0.0.2.dist-info/RECORD
