Metadata-Version: 2.4
Name: pullup
Version: 0.0.2
Summary: pulumi on `roids
Home-page: https://github.com/Karthik777/pullup
Author: Karthik Rajgopal
Author-email: karthik.rajgopal@hotmail.com
License: Apache Software License 2.0
Keywords: nbdev jupyter notebook python
Classifier: Development Status :: 4 - Beta
Classifier: Intended Audience :: Developers
Classifier: Natural Language :: English
Classifier: Programming Language :: Python :: 3.10
Classifier: Programming Language :: Python :: 3.11
Classifier: Programming Language :: Python :: 3.12
Classifier: License :: OSI Approved :: Apache Software License
Requires-Python: >=3.10
License-File: LICENSE
Requires-Dist: fastcore>=1.8.17
Requires-Dist: pulumi>=3.210.0
Requires-Dist: pulumi-aws>=7.13.0
Requires-Dist: pulumi-azure>=6.30.0
Requires-Dist: pulumi-gcp>=9.6.0
Provides-Extra: dev
Dynamic: author
Dynamic: author-email
Dynamic: classifier
Dynamic: description
Dynamic: description-content-type
Dynamic: home-page
Dynamic: keywords
Dynamic: license
Dynamic: license-file
Dynamic: provides-extra
Dynamic: requires-python
Dynamic: summary
